[
    {
        "ballot_box_number": 1461,
        "cm_result": {
            "image_url": "https://secim-images.oyveotesi.org/oyveotesi/raw/server/64744_bulk_999999999_1684081376980083217.jpeg",
            "submission_id": 188316,
            "total_vote": 331,
            "votes": {
                "1": 175,
                "3": 131,
                "4": 25
            }
        },
        "mv_result": {
            "image_url": "https://secim-images.oyveotesi.org/oyveotesi/raw/server/769_bulk_999999999_1684087813678710494.jpg",
            "submission_id": 346011,
            "total_vote": 330,
            "votes": {
                "1": 0,
                "10": 13,
                "11": 33,
                "12": 35,
                "13": 12,
                "14": 1,
                "15": 0,
                "16": 0,
                "17": 0,
                "18": 0,
                "19": 0,
                "2": 1,
                "20": 0,
                "21": 60,
                "22": 23,
                "23": 1,
                "24": 18,
                "3": 0,
                "4": 0,
                "5": 0,
                "6": 0,
                "7": 5,
                "8": 7,
                "9": 121
            }
        },
        "school_name": "YUNUS EMRE ORTAOKULU-İMAM HATİP ORTAOKULU"
    },
    {
        "ballot_box_number": 1465,
        "cm_result": {
            "image_url": "https://secim-images.oyveotesi.org/oyveotesi/raw/client/63318_cb_1093695027_1684082778861346123.jpg",
            "submission_id": 205104,
            "total_vote": 332,
            "votes": {
                "1": 189,
                "2": 0,
                "3": 117,
                "4": 26
            }
        },
        "mv_result": {
            "image_url": "https://secim-images.oyveotesi.org/oyveotesi/raw/client/63318_mv_1083695027_1684084371952540782.jpg",
            "submission_id": 237269,
            "total_vote": 328,
            "votes": {
                "1": 1,
                "10": 20,
                "11": 33,
                "12": 24,
                "13": 3,
                "21": 65,
                "22": 21,
                "23": 1,
                "24": 10,
                "7": 6,
                "8": 2,
                "9": 142
            }
        },
        "school_name": "YUNUS EMRE ORTAOKULU-İMAM HATİP ORTAOKULU"
    },
    {
        "ballot_box_number": 1462,
        "cm_result": {
            "image_url": "https://secim-images.oyveotesi.org/oyveotesi/raw/server/54723_bulk_999999999_1684082197829822433.jpg",
            "submission_id": 197009,
            "total_vote": 336,
            "votes": {
                "1": 181,
                "2": 1,
                "3": 134,
                "4": 20
            }
        },
        "mv_result": null,
        "school_name": "YUNUS EMRE ORTAOKULU-İMAM HATİP ORTAOKULU"
    },
    {
        "ballot_box_number": 1486,
        "cm_result": {
            "image_url": "https://secim-images.oyveotesi.org/oyveotesi/raw/server/769_bulk_999999999_1684087182891006538.jpg",
            "submission_id": 325397,
            "total_vote": 338,
            "votes": {
                "1": 199,
                "2": 1,
                "3": 123,
                "4": 15
            }
        },
        "mv_result": {
            "image_url": "https://secim-images.oyveotesi.org/oyveotesi/raw/server/769_bulk_999999999_1684098434082652904.jpg",
            "submission_id": 527209,
            "total_vote": 328,
            "votes": {
                "1": 0,
                "10": 21,
                "11": 30,
                "12": 34,
                "13": 13,
                "14": 0,
                "15": 0,
                "16": 0,
                "17": 0,
                "18": 0,
                "19": 0,
                "2": 0,
                "20": 0,
                "21": 48,
                "22": 22,
                "23": 4,
                "24": 7,
                "3": 1,
                "4": 0,
                "5": 0,
                "6": 2,
                "7": 2,
                "8": 8,
                "9": 136
            }
        },
        "school_name": "YUNUS EMRE ORTAOKULU-İMAM HATİP ORTAOKULU"
    },
    {
        "ballot_box_number": 1482,
        "cm_result": {
            "image_url": "https://secim-images.oyveotesi.org/oyveotesi/raw/server/769_bulk_999999999_1684087445458178248.jpg",
            "submission_id": 334149,
            "total_vote": 340,
            "votes": {
                "1": 203,
                "3": 110,
                "4": 27
            }
        },
        "mv_result": {
            "image_url": "https://secim-images.oyveotesi.org/oyveotesi/raw/server/769_bulk_999999999_1684087445376750736.jpg",
            "submission_id": 334145,
            "total_vote": 331,
            "votes": {
                "1": 0,
                "10": 29,
                "11": 20,
                "12": 44,
                "13": 2,
                "14": 0,
                "15": 0,
                "16": 0,
                "17": 0,
                "18": 0,
                "19": 0,
                "2": 0,
                "20": 0,
                "21": 36,
                "22": 34,
                "23": 2,
                "24": 17,
                "3": 0,
                "4": 0,
                "5": 0,
                "6": 0,
                "7": 2,
                "8": 2,
                "9": 143
            }
        },
        "school_name": "YUNUS EMRE ORTAOKULU-İMAM HATİP ORTAOKULU"
    },
    {
        "ballot_box_number": 1485,
        "cm_result": {
            "image_url": "https://secim-images.oyveotesi.org/oyveotesi/raw/server/769_bulk_999999999_1684092603998529575.jpg",
            "submission_id": 458718,
            "total_vote": 333,
            "votes": {
                "1": 191,
                "2": 3,
                "3": 111,
                "4": 28
            }
        },
        "mv_result": {
            "image_url": "https://secim-images.oyveotesi.org/oyveotesi/raw/client/769_mv_1083695187_1684092947189113087.jpg",
            "submission_id": 463222,
            "total_vote": 322,
            "votes": {
                "1": 1,
                "10": 20,
                "11": 41,
                "12": 27,
                "13": 5,
                "14": 1,
                "21": 63,
                "22": 14,
                "24": 13,
                "6": 3,
                "7": 3,
                "8": 1,
                "9": 130
            }
        },
        "school_name": "YUNUS EMRE ORTAOKULU-İMAM HATİP ORTAOKULU"
    },
    {
        "ballot_box_number": 1460,
        "cm_result": {
            "image_url": "https://secim-images.oyveotesi.org/oyveotesi/raw/server/769_bulk_999999999_1684095125381545420.jpg",
            "submission_id": 499913,
            "total_vote": 331,
            "votes": {
                "1": 174,
                "2": 4,
                "3": 130,
                "4": 23
            }
        },
        "mv_result": null,
        "school_name": "YUNUS EMRE ORTAOKULU-İMAM HATİP ORTAOKULU"
    },
    {
        "ballot_box_number": 1463,
        "cm_result": {
            "image_url": "https://secim-images.oyveotesi.org/oyveotesi/raw/server/769_bulk_999999999_1684091353507342057.jpg",
            "submission_id": 438723,
            "total_vote": 332,
            "votes": {
                "1": 203,
                "2": 1,
                "3": 114,
                "4": 14
            }
        },
        "mv_result": null,
        "school_name": "YUNUS EMRE ORTAOKULU-İMAM HATİP ORTAOKULU"
    },
    {
        "ballot_box_number": 1477,
        "cm_result": {
            "image_url": "https://secim-images.oyveotesi.org/oyveotesi/raw/server/769_bulk_999999999_1684087328730344373.jpg",
            "submission_id": 330329,
            "total_vote": 344,
            "votes": {
                "1": 199,
                "2": 1,
                "3": 115,
                "4": 29
            }
        },
        "mv_result": null,
        "school_name": "YUNUS EMRE ORTAOKULU-İMAM HATİP ORTAOKULU"
    },
    {
        "ballot_box_number": 1464,
        "cm_result": {
            "image_url": "https://secim-images.oyveotesi.org/oyveotesi/raw/client/21051_cb_1093695026_1684085805549368826.jpg",
            "submission_id": 278576,
            "total_vote": 346,
            "votes": {
                "1": 194,
                "2": 1,
                "3": 131,
                "4": 20
            }
        },
        "mv_result": {
            "image_url": "https://secim-images.oyveotesi.org/oyveotesi/raw/client/21051_cb_1093695026_1684085715277556178.jpg",
            "submission_id": 275573,
            "total_vote": 331,
            "votes": {
                "1": 1,
                "10": 11,
                "11": 35,
                "12": 37,
                "13": 11,
                "15": 1,
                "21": 60,
                "22": 14,
                "24": 12,
                "7": 5,
                "8": 2,
                "9": 142
            }
        },
        "school_name": "YUNUS EMRE ORTAOKULU-İMAM HATİP ORTAOKULU"
    },
    {
        "ballot_box_number": 1475,
        "cm_result": {
            "image_url": "https://source3-secim-images.oyveotesi.org/raw/bulk_download/v2/b058050e-1369-4217-8545-3e4ec86e053c-1684105151934966981.jpg",
            "submission_id": 584088,
            "total_vote": 337,
            "votes": {
                "1": 194,
                "2": 0,
                "3": 114,
                "4": 29
            }
        },
        "mv_result": {
            "image_url": "https://source3-secim-images.oyveotesi.org/raw/bulk_download/v2/8e230e61-9095-44c5-abba-5cd22f859e4f-1684105135335328991.jpg",
            "submission_id": 580691,
            "total_vote": 336,
            "votes": {
                "1": 1,
                "10": 16,
                "11": 31,
                "12": 31,
                "13": 7,
                "14": 0,
                "2": 0,
                "20": 0,
                "21": 56,
                "22": 26,
                "23": 0,
                "24": 14,
                "6": 1,
                "7": 3,
                "8": 4,
                "9": 146
            }
        },
        "school_name": "YUNUS EMRE ORTAOKULU-İMAM HATİP ORTAOKULU"
    },
    {
        "ballot_box_number": 1489,
        "cm_result": {
            "image_url": "https://secim-images.oyveotesi.org/oyveotesi/raw/client/769_cb_1093695191_1684092859548198453.jpg",
            "submission_id": 462082,
            "total_vote": 337,
            "votes": {
                "1": 196,
                "2": 2,
                "3": 124,
                "4": 15
            }
        },
        "mv_result": null,
        "school_name": "YUNUS EMRE ORTAOKULU-İMAM HATİP ORTAOKULU"
    },
    {
        "ballot_box_number": 1457,
        "cm_result": {
            "image_url": "https://source3-secim-images.oyveotesi.org/raw/bulk_download/v2/1d2788a6-a35f-4059-b4cd-08e4eeb2cec9-1684106070253471509.jpg",
            "submission_id": 734726,
            "total_vote": 320,
            "votes": {
                "1": 195,
                "2": 3,
                "3": 106,
                "4": 16
            }
        },
        "mv_result": {
            "image_url": "https://secim-images.oyveotesi.org/oyveotesi/raw/server/769_bulk_999999999_1684091793210341765.jpg",
            "submission_id": 445884,
            "total_vote": 314,
            "votes": {
                "1": 0,
                "10": 13,
                "11": 28,
                "12": 19,
                "13": 3,
                "14": 0,
                "15": 1,
                "16": 0,
                "17": 0,
                "18": 0,
                "19": 0,
                "2": 0,
                "20": 0,
                "21": 47,
                "22": 40,
                "23": 1,
                "24": 5,
                "3": 1,
                "4": 0,
                "5": 1,
                "6": 2,
                "7": 1,
                "8": 3,
                "9": 149
            }
        },
        "school_name": "YUNUS EMRE ORTAOKULU-İMAM HATİP ORTAOKULU"
    },
    {
        "ballot_box_number": 1484,
        "cm_result": {
            "image_url": "https://secim-images.oyveotesi.org/oyveotesi/raw/server/769_bulk_999999999_1684092706293779896.jpg",
            "submission_id": 459940,
            "total_vote": 336,
            "votes": {
                "1": 180,
                "2": 1,
                "3": 131,
                "4": 24
            }
        },
        "mv_result": {
            "image_url": "https://secim-images.oyveotesi.org/oyveotesi/raw/server/769_bulk_999999999_1684092706202079104.jpg",
            "submission_id": 459935,
            "total_vote": 333,
            "votes": {
                "10": 18,
                "11": 20,
                "12": 45,
                "13": 7,
                "14": 1,
                "15": 1,
                "21": 58,
                "22": 13,
                "23": 2,
                "24": 14,
                "4": 1,
                "5": 2,
                "6": 2,
                "7": 4,
                "8": 4,
                "9": 141
            }
        },
        "school_name": "YUNUS EMRE ORTAOKULU-İMAM HATİP ORTAOKULU"
    },
    {
        "ballot_box_number": 1466,
        "cm_result": {
            "image_url": "https://secim-images.oyveotesi.org/oyveotesi/raw/client/42193_cb_1093695028_1684088303783127171.jpg",
            "submission_id": 361463,
            "total_vote": 343,
            "votes": {
                "1": 200,
                "2": 1,
                "3": 107,
                "4": 35
            }
        },
        "mv_result": {
            "image_url": "https://secim-images.oyveotesi.org/oyveotesi/raw/server/769_bulk_999999999_1684088204288769314.jpg",
            "submission_id": 358365,
            "total_vote": 332,
            "votes": {
                "1": 0,
                "10": 21,
                "11": 37,
                "12": 26,
                "13": 6,
                "14": 0,
                "15": 0,
                "16": 0,
                "17": 0,
                "18": 0,
                "19": 0,
                "2": 0,
                "20": 0,
                "21": 56,
                "22": 20,
                "23": 0,
                "24": 16,
                "3": 0,
                "4": 0,
                "5": 6,
                "6": 0,
                "7": 6,
                "8": 5,
                "9": 133
            }
        },
        "school_name": "YUNUS EMRE ORTAOKULU-İMAM HATİP ORTAOKULU"
    },
    {
        "ballot_box_number": 1481,
        "cm_result": {
            "image_url": "https://secim-images.oyveotesi.org/oyveotesi/raw/client/769_cb_1093695183_1684082760634287181.jpg",
            "submission_id": 204805,
            "total_vote": 338,
            "votes": {
                "1": 196,
                "2": 0,
                "3": 125,
                "4": 17
            }
        },
        "mv_result": {
            "image_url": "https://secim-images.oyveotesi.org/oyveotesi/raw/server/769_bulk_999999999_1684091102265946133.jpg",
            "submission_id": 433910,
            "total_vote": 334,
            "votes": {
                "10": 15,
                "11": 37,
                "12": 38,
                "13": 2,
                "21": 65,
                "22": 23,
                "23": 2,
                "24": 12,
                "6": 2,
                "7": 4,
                "8": 1,
                "9": 133
            }
        },
        "school_name": "YUNUS EMRE ORTAOKULU-İMAM HATİP ORTAOKULU"
    },
    {
        "ballot_box_number": 1483,
        "cm_result": {
            "image_url": "https://secim-images.oyveotesi.org/oyveotesi/raw/server/9586_bulk_999999999_1684083464907876263.jpg",
            "submission_id": 217126,
            "total_vote": 340,
            "votes": {
                "1": 192,
                "2": 1,
                "3": 123,
                "4": 24
            }
        },
        "mv_result": {
            "image_url": "https://secim-images.oyveotesi.org/oyveotesi/raw/client/9586_mv_1083695185_1684089736887327249.jpg",
            "submission_id": 402764,
            "total_vote": 332,
            "votes": {
                "10": 16,
                "11": 32,
                "12": 46,
                "13": 1,
                "15": 0,
                "16": 0,
                "17": 0,
                "18": 0,
                "19": 0,
                "20": 0,
                "21": 58,
                "22": 15,
                "23": 1,
                "24": 20,
                "6": 0,
                "7": 3,
                "8": 5,
                "9": 135
            }
        },
        "school_name": "YUNUS EMRE ORTAOKULU-İMAM HATİP ORTAOKULU"
    },
    {
        "ballot_box_number": 1472,
        "cm_result": {
            "image_url": "https://secim-images.oyveotesi.org/oyveotesi/raw/server/769_bulk_999999999_1684088250201782918.jpg",
            "submission_id": 359801,
            "total_vote": 330,
            "votes": {
                "1": 201,
                "2": 0,
                "3": 103,
                "4": 26
            }
        },
        "mv_result": {
            "image_url": "https://secim-images.oyveotesi.org/oyveotesi/raw/server/769_bulk_999999999_1684088250089269800.jpg",
            "submission_id": 359795,
            "total_vote": 331,
            "votes": {
                "10": 18,
                "11": 50,
                "12": 35,
                "13": 4,
                "14": 0,
                "15": 0,
                "16": 0,
                "17": 0,
                "18": 1,
                "19": 0,
                "20": 0,
                "21": 49,
                "22": 15,
                "23": 0,
                "24": 14,
                "5": 0,
                "6": 2,
                "7": 2,
                "8": 6,
                "9": 135
            }
        },
        "school_name": "YUNUS EMRE ORTAOKULU-İMAM HATİP ORTAOKULU"
    },
    {
        "ballot_box_number": 1478,
        "cm_result": {
            "image_url": "https://source3-secim-images.oyveotesi.org/raw/bulk_download/v2/3d25a29d-bb34-4951-aefb-c00ce75a7fd6-1684105260986057295.jpeg",
            "submission_id": 606707,
            "total_vote": 324,
            "votes": {
                "1": 179,
                "2": 2,
                "3": 126,
                "4": 17
            }
        },
        "mv_result": {
            "image_url": "https://source3-secim-images.oyveotesi.org/raw/bulk_download/v2/510f90bf-9d28-48de-807b-c7ba3c7db894-1684105173425680517.jpg",
            "submission_id": 589263,
            "total_vote": 323,
            "votes": {
                "1": 0,
                "10": 10,
                "11": 22,
                "12": 38,
                "13": 5,
                "14": 1,
                "15": 1,
                "16": 0,
                "17": 0,
                "18": 0,
                "19": 1,
                "2": 0,
                "20": 0,
                "21": 63,
                "22": 25,
                "23": 0,
                "24": 10,
                "3": 0,
                "4": 0,
                "5": 0,
                "6": 0,
                "7": 9,
                "8": 7,
                "9": 131
            }
        },
        "school_name": "YUNUS EMRE ORTAOKULU-İMAM HATİP ORTAOKULU"
    },
    {
        "ballot_box_number": 1474,
        "cm_result": {
            "image_url": "https://secim-images.oyveotesi.org/oyveotesi/raw/server/769_bulk_999999999_1684090195347907610.jpg",
            "submission_id": 414415,
            "total_vote": 334,
            "votes": {
                "1": 200,
                "2": 1,
                "3": 103,
                "4": 30
            }
        },
        "mv_result": {
            "image_url": "https://source3-secim-images.oyveotesi.org/raw/bulk_download/v2/7a89b8ed-2562-40f9-acf5-4f51654e40c2-1684105169783637798.jpg",
            "submission_id": 588142,
            "total_vote": 333,
            "votes": {
                "10": 19,
                "11": 34,
                "12": 32,
                "13": 2,
                "21": 45,
                "22": 29,
                "24": 13,
                "6": 3,
                "7": 5,
                "8": 3,
                "9": 148
            }
        },
        "school_name": "YUNUS EMRE ORTAOKULU-İMAM HATİP ORTAOKULU"
    },
    {
        "ballot_box_number": 1473,
        "cm_result": {
            "image_url": "https://secim-images.oyveotesi.org/oyveotesi/raw/client/21051_cb_1093695175_1684085418060132651.jpg",
            "submission_id": 266185,
            "total_vote": 339,
            "votes": {
                "1": 184,
                "2": 2,
                "3": 127,
                "4": 26
            }
        },
        "mv_result": {
            "image_url": "https://secim-images.oyveotesi.org/oyveotesi/raw/client/21051_cb_1093695175_1684085326596888535.jpg",
            "submission_id": 263516,
            "total_vote": 334,
            "votes": {
                "10": 21,
                "11": 26,
                "12": 30,
                "13": 7,
                "21": 70,
                "22": 21,
                "24": 8,
                "5": 1,
                "7": 4,
                "8": 5,
                "9": 141
            }
        },
        "school_name": "YUNUS EMRE ORTAOKULU-İMAM HATİP ORTAOKULU"
    },
    {
        "ballot_box_number": 1488,
        "cm_result": {
            "image_url": "https://secim-images.oyveotesi.org/oyveotesi/raw/server/769_bulk_999999999_1684093815518707479.jpg",
            "submission_id": 474632,
            "total_vote": 338,
            "votes": {
                "1": 198,
                "2": 0,
                "3": 111,
                "4": 29
            }
        },
        "mv_result": null,
        "school_name": "YUNUS EMRE ORTAOKULU-İMAM HATİP ORTAOKULU"
    },
    {
        "ballot_box_number": 1479,
        "cm_result": {
            "image_url": "https://secim-images.oyveotesi.org/oyveotesi/raw/server/769_bulk_999999999_1684086975485059937.jpg",
            "submission_id": 318119,
            "total_vote": 328,
            "votes": {
                "1": 207,
                "2": 0,
                "3": 105,
                "4": 16
            }
        },
        "mv_result": {
            "image_url": "https://source3-secim-images.oyveotesi.org/raw/bulk_download/v2/a782e956-61b4-48f5-84f0-6c09fa2cbad5-1684105176959994379.jpg",
            "submission_id": 589413,
            "total_vote": 327,
            "votes": {
                "1": 0,
                "10": 14,
                "11": 28,
                "12": 44,
                "13": 10,
                "14": 1,
                "15": 0,
                "16": 0,
                "17": 2,
                "18": 0,
                "19": 0,
                "2": 0,
                "20": 1,
                "21": 40,
                "22": 12,
                "23": 2,
                "24": 3,
                "3": 0,
                "4": 0,
                "5": 4,
                "6": 0,
                "7": 6,
                "8": 2,
                "9": 158
            }
        },
        "school_name": "YUNUS EMRE ORTAOKULU-İMAM HATİP ORTAOKULU"
    },
    {
        "ballot_box_number": 1471,
        "cm_result": {
            "image_url": "https://secim-images.oyveotesi.org/oyveotesi/raw/client/769_cb_1093695033_1684085112397246022.jpg",
            "submission_id": 257294,
            "total_vote": 334,
            "votes": {
                "1": 199,
                "2": 1,
                "3": 111,
                "4": 23
            }
        },
        "mv_result": {
            "image_url": "https://secim-images.oyveotesi.org/oyveotesi/raw/client/769_mv_1083695033_1684085122701185158.jpg",
            "submission_id": 257572,
            "total_vote": 336,
            "votes": {
                "10": 18,
                "11": 37,
                "12": 39,
                "13": 4,
                "14": 1,
                "15": 0,
                "16": 0,
                "17": 0,
                "18": 0,
                "19": 0,
                "20": 0,
                "21": 56,
                "22": 19,
                "23": 1,
                "24": 7,
                "5": 1,
                "6": 1,
                "7": 3,
                "8": 1,
                "9": 148
            }
        },
        "school_name": "YUNUS EMRE ORTAOKULU-İMAM HATİP ORTAOKULU"
    },
    {
        "ballot_box_number": 1459,
        "cm_result": {
            "image_url": "https://secim-images.oyveotesi.org/oyveotesi/raw/client/21051_cb_1093695021_1684081007876985132.jpg",
            "submission_id": 185377,
            "total_vote": 329,
            "votes": {
                "1": 187,
                "2": 0,
                "3": 120,
                "4": 22
            }
        },
        "mv_result": {
            "image_url": "https://secim-images.oyveotesi.org/oyveotesi/raw/client/21051_mv_1083695021_1684083273204888868.jpg",
            "submission_id": 213450,
            "total_vote": 334,
            "votes": {
                "10": 12,
                "11": 44,
                "12": 29,
                "13": 6,
                "21": 75,
                "22": 16,
                "24": 11,
                "4": 1,
                "5": 1,
                "7": 5,
                "8": 5,
                "9": 129
            }
        },
        "school_name": "YUNUS EMRE ORTAOKULU-İMAM HATİP ORTAOKULU"
    },
    {
        "ballot_box_number": 1487,
        "cm_result": {
            "image_url": "https://secim-images.oyveotesi.org/oyveotesi/raw/server/769_bulk_999999999_1684093815685352548.jpg",
            "submission_id": 474635,
            "total_vote": 340,
            "votes": {
                "1": 215,
                "2": 2,
                "3": 99,
                "4": 24
            }
        },
        "mv_result": {
            "image_url": "https://source3-secim-images.oyveotesi.org/raw/bulk_download/v2/c2fc06b8-fbc2-435e-8bb3-6e7c5924c239-1684105132513971960.jpg",
            "submission_id": 580109,
            "total_vote": 334,
            "votes": {
                "10": 11,
                "11": 30,
                "12": 33,
                "13": 9,
                "2": 1,
                "21": 44,
                "22": 24,
                "23": 1,
                "24": 7,
                "3": 1,
                "5": 2,
                "6": 2,
                "7": 7,
                "8": 2,
                "9": 160
            }
        },
        "school_name": "YUNUS EMRE ORTAOKULU-İMAM HATİP ORTAOKULU"
    },
    {
        "ballot_box_number": 1455,
        "cm_result": {
            "image_url": "https://secim-images.oyveotesi.org/oyveotesi/raw/client/30613_cb_1093695017_1684084948085225798.jpg",
            "submission_id": 252622,
            "total_vote": 305,
            "votes": {
                "1": 184,
                "2": 2,
                "3": 98,
                "4": 21
            }
        },
        "mv_result": null,
        "school_name": "YUNUS EMRE ORTAOKULU-İMAM HATİP ORTAOKULU"
    },
    {
        "ballot_box_number": 1470,
        "cm_result": {
            "image_url": "https://secim-images.oyveotesi.org/oyveotesi/raw/client/769_cb_1093695032_1684083654858811284.jpg",
            "submission_id": 220887,
            "total_vote": 354,
            "votes": {
                "1": 221,
                "3": 102,
                "4": 31
            }
        },
        "mv_result": {
            "image_url": "https://secim-images.oyveotesi.org/oyveotesi/raw/server/50273_bulk_999999999_1684086675415264049.jpeg",
            "submission_id": 307620,
            "total_vote": 342,
            "votes": {
                "1": 1,
                "10": 22,
                "11": 42,
                "12": 44,
                "13": 4,
                "14": 0,
                "15": 0,
                "16": 0,
                "17": 0,
                "18": 1,
                "19": 0,
                "2": 0,
                "20": 0,
                "21": 41,
                "22": 16,
                "23": 0,
                "24": 19,
                "3": 0,
                "4": 0,
                "5": 1,
                "6": 2,
                "7": 2,
                "8": 4,
                "9": 143
            }
        },
        "school_name": "YUNUS EMRE ORTAOKULU-İMAM HATİP ORTAOKULU"
    },
    {
        "ballot_box_number": 1476,
        "cm_result": {
            "image_url": "https://secim-images.oyveotesi.org/oyveotesi/raw/client/73325_cb_1093695178_1684081350324093830.jpg",
            "submission_id": 188072,
            "total_vote": 335,
            "votes": {
                "1": 206,
                "2": 1,
                "3": 108,
                "4": 20
            }
        },
        "mv_result": {
            "image_url": "https://secim-images.oyveotesi.org/oyveotesi/raw/client/73325_mv_1083695178_1684088251433934045.jpg",
            "submission_id": 359843,
            "total_vote": 331,
            "votes": {
                "1": 0,
                "10": 18,
                "11": 26,
                "12": 29,
                "13": 7,
                "14": 0,
                "15": 2,
                "16": 0,
                "17": 0,
                "18": 0,
                "19": 0,
                "2": 0,
                "20": 0,
                "21": 54,
                "22": 22,
                "23": 1,
                "24": 13,
                "3": 0,
                "4": 0,
                "5": 1,
                "6": 1,
                "7": 4,
                "8": 9,
                "9": 144
            }
        },
        "school_name": "YUNUS EMRE ORTAOKULU-İMAM HATİP ORTAOKULU"
    },
    {
        "ballot_box_number": 1468,
        "cm_result": {
            "image_url": "https://secim-images.oyveotesi.org/oyveotesi/raw/server/769_bulk_999999999_1684090011548188112.jpg",
            "submission_id": 410043,
            "total_vote": 339,
            "votes": {
                "1": 197,
                "2": 0,
                "3": 122,
                "4": 20
            }
        },
        "mv_result": null,
        "school_name": "YUNUS EMRE ORTAOKULU-İMAM HATİP ORTAOKULU"
    },
    {
        "ballot_box_number": 1467,
        "cm_result": {
            "image_url": "https://secim-images.oyveotesi.org/oyveotesi/raw/server/769_bulk_999999999_1684091693606487834.jpg",
            "submission_id": 444328,
            "total_vote": 335,
            "votes": {
                "1": 214,
                "2": 0,
                "3": 102,
                "4": 19
            }
        },
        "mv_result": {
            "image_url": "https://secim-images.oyveotesi.org/oyveotesi/raw/client/769_mv_1083695029_1684094381334479548.jpg",
            "submission_id": 491287,
            "total_vote": 333,
            "votes": {
                "1": 4,
                "10": 25,
                "11": 43,
                "12": 25,
                "13": 5,
                "14": 2,
                "21": 39,
                "22": 37,
                "23": 1,
                "24": 8,
                "8": 4,
                "9": 140
            }
        },
        "school_name": "YUNUS EMRE ORTAOKULU-İMAM HATİP ORTAOKULU"
    },
    {
        "ballot_box_number": 1480,
        "cm_result": {
            "image_url": "https://secim-images.oyveotesi.org/oyveotesi/raw/client/64786_cb_1093695182_1684082560912827576.jpg",
            "submission_id": 201796,
            "total_vote": 335,
            "votes": {
                "1": 189,
                "2": 0,
                "3": 123,
                "4": 23
            }
        },
        "mv_result": {
            "image_url": "https://secim-images.oyveotesi.org/oyveotesi/raw/client/64786_mv_1083695182_1684086882491529094.jpg",
            "submission_id": 314891,
            "total_vote": 329,
            "votes": {
                "10": 10,
                "11": 40,
                "12": 21,
                "13": 13,
                "21": 61,
                "22": 24,
                "24": 18,
                "6": 1,
                "7": 3,
                "8": 1,
                "9": 137
            }
        },
        "school_name": "YUNUS EMRE ORTAOKULU-İMAM HATİP ORTAOKULU"
    },
    {
        "ballot_box_number": 1456,
        "cm_result": {
            "image_url": "https://secim-images.oyveotesi.org/oyveotesi/raw/client/22956_cb_1093695018_1684084795502097166.jpg",
            "submission_id": 248416,
            "total_vote": 330,
            "votes": {
                "1": 198,
                "2": 1,
                "3": 112,
                "4": 19
            }
        },
        "mv_result": {
            "image_url": "https://secim-images.oyveotesi.org/oyveotesi/raw/client/22956_mv_1083695018_1684086844492337530.jpg",
            "submission_id": 313567,
            "total_vote": 325,
            "votes": {
                "1": 1,
                "10": 13,
                "11": 42,
                "12": 40,
                "13": 8,
                "14": 1,
                "15": 1,
                "16": 0,
                "17": 1,
                "18": 0,
                "19": 0,
                "2": 1,
                "20": 0,
                "21": 47,
                "22": 19,
                "23": 0,
                "24": 8,
                "3": 1,
                "4": 0,
                "5": 0,
                "6": 1,
                "7": 4,
                "8": 3,
                "9": 134
            }
        },
        "school_name": "YUNUS EMRE ORTAOKULU-İMAM HATİP ORTAOKULU"
    },
    {
        "ballot_box_number": 1469,
        "cm_result": {
            "image_url": "https://secim-images.oyveotesi.org/oyveotesi/raw/client/11996_cb_1093695031_1684082932081577215.jpg",
            "submission_id": 207609,
            "total_vote": 333,
            "votes": {
                "1": 184,
                "2": 3,
                "3": 128,
                "4": 18
            }
        },
        "mv_result": {
            "image_url": "https://secim-images.oyveotesi.org/oyveotesi/raw/client/11996_mv_1083695031_1684085725684379488.jpg",
            "submission_id": 275929,
            "total_vote": 326,
            "votes": {
                "10": 22,
                "11": 31,
                "12": 28,
                "13": 6,
                "15": 1,
                "21": 64,
                "22": 26,
                "23": 1,
                "24": 11,
                "6": 1,
                "7": 1,
                "8": 4,
                "9": 130
            }
        },
        "school_name": "YUNUS EMRE ORTAOKULU-İMAM HATİP ORTAOKULU"
    },
    {
        "ballot_box_number": 1458,
        "cm_result": {
            "image_url": "https://secim-images.oyveotesi.org/oyveotesi/raw/client/42182_cb_1093695020_1684085021897980735.jpg",
            "submission_id": 254791,
            "total_vote": 331,
            "votes": {
                "1": 188,
                "2": 0,
                "3": 114,
                "4": 29
            }
        },
        "mv_result": {
            "image_url": "https://secim-images.oyveotesi.org/oyveotesi/raw/client/42182_mv_1083695020_1684084625735939475.jpg",
            "submission_id": 243821,
            "total_vote": 324,
            "votes": {
                "1": 1,
                "10": 12,
                "11": 37,
                "12": 46,
                "13": 3,
                "21": 42,
                "22": 26,
                "23": 2,
                "24": 15,
                "5": 1,
                "6": 2,
                "7": 5,
                "8": 4,
                "9": 128
            }
        },
        "school_name": "YUNUS EMRE ORTAOKULU-İMAM HATİP ORTAOKULU"
    }
]